Workbook

Sheet Pivot_Analysis
A3: Row Labels | B3: Sum of Revenue
A4: East | B4: 54045
A5: North | B5: 52150
A6: South | B6: 20280
A7: West | B7: 33725
A8: Grand Total | B8: 160200
A20: Row Labels | B20: Total Revenue | C20: % of Grand Total
A21: Electronics | B21: 3230 | C21: 0.020162297
A22: Furniture | B22: 156700 | C22: 0.97815231
A23: Lighting | B23: 270 | C23: 0.0016853933
A24: Grand Total | B24: 160200 | C24: 1
A40: Row Labels | B40: Sum of Revenue 2
A41: Jan | B41: 8395
A42: Feb | B42: 6300
A43: Mar | B43: 12280
A44: Apr | B44: 29545
A45: May | B45: 30800
A46: Jun | B46: 72880
A47: Grand Total | B47: 160200

Sheet Dashboard
B2: HEADLINE PERFORMANCE KPIs
B3: TOTAL REVENUE | C3: AVG ORDER VALUE | D3: TOTAL ORDERS | E3: LARGEST ORDER | F3: SMALLEST ORDER
B4: =SUM(Data_Clean!K2:K36) -> 160200 | C4: =AVERAGE(Data_Clean!K2:K36) -> 4577.1429 | D4: =COUNTA(Data_Clean!A2:A36) -> 35 | E4: =MAX(Data_Clean!K2:K36) -> 24300 | F4: =MIN(Data_Clean!K2:K36) -> 45
B18: 📊 Executive Findings & Strategic Recommendations
B20: Key Insights
B21: Dominant Territory: The North Region generated the highest total revenue ($52,150, ~32.5% of total sales), driven heavily by high-margin corporate workstation upgrades (Standing Desk Pro and Apex Ergonomic Chair).
B22: Primary Revenue Driver: Furniture is our highest-earning category (over 50% of overall revenue), whereas Lighting accounts for high unit volume (e.g., Lumina Desk Lamps) but small overall revenue contribution.
B23: Mid-Year Surge: Sales peaked dramatically in June 2026 ($72,880), representing nearly 45% of total 6-month revenue due to corporate mid-year budget allocations and end-of-quarter volume buying.
B25: Recommendations
B26: Upsell Low-Performing Regions: The South region yielded the lowest revenue ($20,280). Introduce product bundling (e.g., pair a Lumina Desk Lamp with an UltraWide Monitor) at a slight discount to increase South Region Average Order Value.
B27: Corporate Sales Focus: Order values >= $5,000 came almost exclusively from the Corporate segment. Assign dedicated key-account managers to corporate clients to lock in repeat workstation orders before Q4.
B28: Inventory Management: Increase stock reserves for P105 Standing Desk Pro starting in May to avoid fulfillment delays during the June demand peak.

Sheet Product_Catalog
A1: Product ID | B1: Product Name | C1: Category | D1: Unit Price
A2: P101 | B2: Lumina Desk Lamp | C2: Lighting | D2: 45
A3: P102 | B3: UltraWide Monitor | C3: Electronics | D3: 350
A4: P103 | B4: Wireless Keyboard | C4: Electronics | D4: 60
A5: P104 | B5: Apex Ergonomic Chair | C5: Furniture | D5: 250
A6: P105 | B6: Standing Desk Pro | C6: Furniture | D6: 900

Sheet Data_Clean
A1: Order ID | B1: Date | C1: Raw Region | D1: Clean Region | E1: Product ID | F1: Units | G1: Customer Segment | H1: Product Name | I1: Category | J1: Unit Price | K1: Revenue | L1: Month | M1: Order Tier
A2: ORD-001 | B2: 46177 | C2: north | D2: =PROPER(TRIM(C2)) -> North | E2: P105 | F2: 13 | G2: Corporate | H2: =_xlfn.XLOOKUP(E2, Product_Catalog!$A$2:$A$6, Product_Catalog!$B$2:$B$6, "Unknown") -> Standing Desk Pro | I2: =_xlfn.XLOOKUP(E2, Product_Catalog!$A$2:$A$6, Product_Catalog!$C$2:$C$6, "Unknown") -> Furniture | J2: =_xlfn.XLOOKUP(E2, Product_Catalog!$A$2:$A$6, Product_Catalog!$D$2:$D$6, 0) -> 900 | K2: =F2 * J2 -> 11700 | L2: =TEXT(B2, "mmm") -> Jun | M2: =IF(K2>=5000, "High Value", "Standard") -> High Value
A3: ORD-002 | B3: 46198 | C3: north | D3: =PROPER(TRIM(C3)) -> North | E3: P105 | F3: 10 | G3: Corporate | H3: =_xlfn.XLOOKUP(E3, Product_Catalog!$A$2:$A$6, Product_Catalog!$B$2:$B$6, "Unknown") -> Standing Desk Pro | I3: =_xlfn.XLOOKUP(E3, Product_Catalog!$A$2:$A$6, Product_Catalog!$C$2:$C$6, "Unknown") -> Furniture | J3: =_xlfn.XLOOKUP(E3, Product_Catalog!$A$2:$A$6, Product_Catalog!$D$2:$D$6, 0) -> 900 | K3: =F3 * J3 -> 9000 | L3: =TEXT(B3, "mmm") -> Jun | M3: =IF(K3>=5000, "High Value", "Standard") -> High Value
A4: ORD-003 | B4: 46182 | C4: south | D4: =PROPER(TRIM(C4)) -> South | E4: P105 | F4: 10 | G4: Corporate | H4: =_xlfn.XLOOKUP(E4, Product_Catalog!$A$2:$A$6, Product_Catalog!$B$2:$B$6, "Unknown") -> Standing Desk Pro | I4: =_xlfn.XLOOKUP(E4, Product_Catalog!$A$2:$A$6, Product_Catalog!$C$2:$C$6, "Unknown") -> Furniture | J4: =_xlfn.XLOOKUP(E4, Product_Catalog!$A$2:$A$6, Product_Catalog!$D$2:$D$6, 0) -> 900 | K4: =F4 * J4 -> 9000 | L4: =TEXT(B4, "mmm") -> Jun | M4: =IF(K4>=5000, "High Value", "Standard") -> High Value
A5: ORD-004 | B5: 46196 | C5: east | D5: =PROPER(TRIM(C5)) -> East | E5: P105 | F5: 20 | G5: Corporate | H5: =_xlfn.XLOOKUP(E5, Product_Catalog!$A$2:$A$6, Product_Catalog!$B$2:$B$6, "Unknown") -> Standing Desk Pro | I5: =_xlfn.XLOOKUP(E5, Product_Catalog!$A$2:$A$6, Product_Catalog!$C$2:$C$6, "Unknown") -> Furniture | J5: =_xlfn.XLOOKUP(E5, Product_Catalog!$A$2:$A$6, Product_Catalog!$D$2:$D$6, 0) -> 900 | K5: =F5 * J5 -> 18000 | L5: =TEXT(B5, "mmm") -> Jun | M5: =IF(K5>=5000, "High Value", "Standard") -> High Value
A6: ORD-005 | B6: 46199 | C6: west | D6: =PROPER(TRIM(C6)) -> West | E6: P105 | F6: 27 | G6: Corporate | H6: =_xlfn.XLOOKUP(E6, Product_Catalog!$A$2:$A$6, Product_Catalog!$B$2:$B$6, "Unknown") -> Standing Desk Pro | I6: =_xlfn.XLOOKUP(E6, Product_Catalog!$A$2:$A$6, Product_Catalog!$C$2:$C$6, "Unknown") -> Furniture | J6: =_xlfn.XLOOKUP(E6, Product_Catalog!$A$2:$A$6, Product_Catalog!$D$2:$D$6, 0) -> 900 | K6: =F6 * J6 -> 24300 | L6: =TEXT(B6, "mmm") -> Jun | M6: =IF(K6>=5000, "High Value", "Standard") -> High Value
A7: ORD-006 | B7: 46195 | C7: west | D7: =PROPER(TRIM(C7)) -> West | E7: P102 | F7: 2 | G7: Consumer | H7: =_xlfn.XLOOKUP(E7, Product_Catalog!$A$2:$A$6, Product_Catalog!$B$2:$B$6, "Unknown") -> UltraWide Monitor | I7: =_xlfn.XLOOKUP(E7, Product_Catalog!$A$2:$A$6, Product_Catalog!$C$2:$C$6, "Unknown") -> Electronics | J7: =_xlfn.XLOOKUP(E7, Product_Catalog!$A$2:$A$6, Product_Catalog!$D$2:$D$6, 0) -> 350 | K7: =F7 * J7 -> 700 | L7: =TEXT(B7, "mmm") -> Jun | M7: =IF(K7>=5000, "High Value", "Standard") -> Standard
A8: ORD-007 | B8: 46197 | C8: west | D8: =PROPER(TRIM(C8)) -> West | E8: P101 | F8: 4 | G8: Small Business | H8: =_xlfn.XLOOKUP(E8, Product_Catalog!$A$2:$A$6, Product_Catalog!$B$2:$B$6, "Unknown") -> Lumina Desk Lamp | I8: =_xlfn.XLOOKUP(E8, Product_Catalog!$A$2:$A$6, Product_Catalog!$C$2:$C$6, "Unknown") -> Lighting | J8: =_xlfn.XLOOKUP(E8, Product_Catalog!$A$2:$A$6, Product_Catalog!$D$2:$D$6, 0) -> 45 | K8: =F8 * J8 -> 180 | L8: =TEXT(B8, "mmm") -> Jun | M8: =IF(K8>=5000, "High Value", "Standard") -> Standard
A9: ORD-008 | B9: 46153 | C9: north | D9: =PROPER(TRIM(C9)) -> North | E9: P105 | F9: 10 | G9: Corporate | H9: =_xlfn.XLOOKUP(E9, Product_Catalog!$A$2:$A$6, Product_Catalog!$B$2:$B$6, "Unknown") -> Standing Desk Pro | I9: =_xlfn.XLOOKUP(E9, Product_Catalog!$A$2:$A$6, Product_Catalog!$C$2:$C$6, "Unknown") -> Furniture | J9: =_xlfn.XLOOKUP(E9, Product_Catalog!$A$2:$A$6, Product_Catalog!$D$2:$D$6, 0) -> 900 | K9: =F9 * J9 -> 9000 | L9: =TEXT(B9, "mmm") -> May | M9: =IF(K9>=5000, "High Value", "Standard") -> High Value
A10: ORD-009 | B10: 46135 | C10: north | D10: =PROPER(TRIM(C10)) -> North | E10: P105 | F10: 10 | G10: Corporate | H10: =_xlfn.XLOOKUP(E10, Product_Catalog!$A$2:$A$6, Product_Catalog!$B$2:$B$6, "Unknown") -> Standing Desk Pro | I10: =_xlfn.XLOOKUP(E10, Product_Catalog!$A$2:$A$6, Product_Catalog!$C$2:$C$6, "Unknown") -> Furniture | J10: =_xlfn.XLOOKUP(E10, Product_Catalog!$A$2:$A$6, Product_Catalog!$D$2:$D$6, 0) -> 900 | K10: =F10 * J10 -> 9000 | L10: =TEXT(B10, "mmm") -> Apr | M10: =IF(K10>=5000, "High Value", "Standard") -> High Value
A11: ORD-010 | B11: 46100 | C11: north | D11: =PROPER(TRIM(C11)) -> North | E11: P105 | F11: 10 | G11: Corporate | H11: =_xlfn.XLOOKUP(E11, Product_Catalog!$A$2:$A$6, Product_Catalog!$B$2:$B$6, "Unknown") -> Standing Desk Pro | I11: =_xlfn.XLOOKUP(E11, Product_Catalog!$A$2:$A$6, Product_Catalog!$C$2:$C$6, "Unknown") -> Furniture | J11: =_xlfn.XLOOKUP(E11, Product_Catalog!$A$2:$A$6, Product_Catalog!$D$2:$D$6, 0) -> 900 | K11: =F11 * J11 -> 9000 | L11: =TEXT(B11, "mmm") -> Mar | M11: =IF(K11>=5000, "High Value", "Standard") -> High Value
A12: ORD-011 | B12: 46068 | C12: north | D12: =PROPER(TRIM(C12)) -> North | E12: P105 | F12: 3 | G12: Corporate | H12: =_xlfn.XLOOKUP(E12, Product_Catalog!$A$2:$A$6, Product_Catalog!$B$2:$B$6, "Unknown") -> Standing Desk Pro | I12: =_xlfn.XLOOKUP(E12, Product_Catalog!$A$2:$A$6, Product_Catalog!$C$2:$C$6, "Unknown") -> Furniture | J12: =_xlfn.XLOOKUP(E12, Product_Catalog!$A$2:$A$6, Product_Catalog!$D$2:$D$6, 0) -> 900 | K12: =F12 * J12 -> 2700 | L12: =TEXT(B12, "mmm") -> Feb | M12: =IF(K12>=5000, "High Value", "Standard") -> Standard
A13: ORD-012 | B13: 46034 | C13: north | D13: =PROPER(TRIM(C13)) -> North | E13: P102 | F13: 5 | G13: Small Business | H13: =_xlfn.XLOOKUP(E13, Product_Catalog!$A$2:$A$6, Product_Catalog!$B$2:$B$6, "Unknown") -> UltraWide Monitor | I13: =_xlfn.XLOOKUP(E13, Product_Catalog!$A$2:$A$6, Product_Catalog!$C$2:$C$6, "Unknown") -> Electronics | J13: =_xlfn.XLOOKUP(E13, Product_Catalog!$A$2:$A$6, Product_Catalog!$D$2:$D$6, 0) -> 350 | K13: =F13 * J13 -> 1750 | L13: =TEXT(B13, "mmm") -> Jan | M13: =IF(K13>=5000, "High Value", "Standard") -> Standard
... A36: ORD-035 | B36: 46132 | C36: west | D36: =PROPER(TRIM(C36)) -> West | E36: P101 | F36: 1 | G36: Small Business | H36: =_xlfn.XLOOKUP(E36, Product_Catalog!$A$2:$A$6, Product_Catalog!$B$2:$B$6, "Unknown") -> Lumina Desk Lamp | I36: =_xlfn.XLOOKUP(E36, Product_Catalog!$A$2:$A$6, Product_Catalog!$C$2:$C$6, "Unknown") -> Lighting | J36: =_xlfn.XLOOKUP(E36, Product_Catalog!$A$2:$A$6, Product_Catalog!$D$2:$D$6, 0) -> 45 | K36: =F36 * J36 -> 45 | L36: =TEXT(B36, "mmm") -> Apr | M36: =IF(K36>=5000, "High Value", "Standard") -> Standard
